nonebot_plugin_cchess/__init__.py
nonebot_plugin_cchess/board.py
nonebot_plugin_cchess/config.py
nonebot_plugin_cchess/drawer.py
nonebot_plugin_cchess/engine.py
nonebot_plugin_cchess/game.py
nonebot_plugin_cchess/migrations/3c19beaf3015_init_db.py
nonebot_plugin_cchess/model.py
nonebot_plugin_cchess/move.py
nonebot_plugin_cchess/piece.py
nonebot_plugin_cchess/resources/images/a_black.png
nonebot_plugin_cchess/resources/images/a_red.png
nonebot_plugin_cchess/resources/images/b_black.png
nonebot_plugin_cchess/resources/images/b_red.png
nonebot_plugin_cchess/resources/images/board_black.png
nonebot_plugin_cchess/resources/images/board_red.png
nonebot_plugin_cchess/resources/images/c_black.png
nonebot_plugin_cchess/resources/images/c_red.png
nonebot_plugin_cchess/resources/images/k_black.png
nonebot_plugin_cchess/resources/images/k_red.png
nonebot_plugin_cchess/resources/images/mark.png
nonebot_plugin_cchess/resources/images/n_black.png
nonebot_plugin_cchess/resources/images/n_red.png
nonebot_plugin_cchess/resources/images/p_black.png
nonebot_plugin_cchess/resources/images/p_red.png
nonebot_plugin_cchess/resources/images/r_black.png
nonebot_plugin_cchess/resources/images/r_red.png
nonebot_plugin_cchess-0.4.2.dist-info/LICENSE
nonebot_plugin_cchess-0.4.2.dist-info/METADATA
nonebot_plugin_cchess-0.4.2.dist-info/WHEEL
nonebot_plugin_cchess-0.4.2.dist-info/RECORD
